[
  {
    "id": 1,
    "name": "کیف",
    "price": 150000,
    "image": "./images/bag.png",
    "alt": "bag product"
  },
  {
    "id": 2,
    "name": "خودکار",
    "price": 10000,
    "image": "./images/pen.png",
    "alt": "pen product"
  },
  {
    "id": 3,
    "name": "دفترچه یادداشت",
    "price": 36000,
    "image": "./images/note-book.png",
    "alt": "note book product"
  },
  {
    "id": 4,
    "name": "مداد رنگی",
    "price": 43000,
    "image": "./images/colored-pencils.png",
    "alt": "colored pencils product"
  },
  {
    "id": 5,
    "name": "مداد",
    "price": 15000,
    "image": "./images/pencil.png",
    "alt": "pencil product"
  },
  {
    "id": 6,
    "name": "خطکش",
    "price": 23000,
    "image": "./images/ruler.png",
    "alt": "ruler product"
  },
  {
    "id": 7,
    "name": "لیوان",
    "price": 28000,
    "image": "./images/mug.png",
    "alt": "mug product"
  },
  {
    "id": 8,
    "name": "پاکن",
    "price": 12000,
    "image": "./images/eraser.png",
    "alt": "eraser product"
  },
  {
    "id": 9,
    "name": "چسب چوب",
    "price": 67000,
    "image": "./images/glue-stick.png",
    "alt": "glue stick product"
  }
]
